[
  {
    "project": "new_today_a",
    "task": {
      "name": "new_today_a",
      "description": "testing_qa_deploy_job",
      "active": true
    },

    "parameters": {
      "contextName": "Default",
      "applyContextToChildren": false,
      "logLevel": "Info",
      "statisticsEnabled": true,
      "onUnavailableJobServer": "WAIT",
      "timeout": 1500,
      "pauseTriggerOnError": false
    },

    "nexus": {
      "repository": "release_ci",
      "groupId": "org.example.ci.job",
      "artifactId": "new_today_a",
      "version": "7.0.1_LATEST"
    },
    "executionServer": "JOB_LAS01"
	

	
	
    
  }
  
]